{
	"name": "wabs_out_csv_file",
	"properties": {
		"linkedServiceName": {
			"referenceName": "lksazureblobstorage",
			"type": "LinkedServiceReference"
		},
		"parameters": {
			"container": {
				"type": "String"
			},
			"directory": {
				"type": "String"
			},
			"filename": {
				"type": "String"
			}
		},
		"annotations": [],
		"type": "DelimitedText",
		"typeProperties": {
			"location": {
				"type": "AzureBlobStorageLocation",
				"fileName": {
					"value": "@dataset().filename",
					"type": "Expression"
				},
				"folderPath": {
					"value": "@dataset().directory",
					"type": "Expression"
				},
				"container": {
					"value": "@dataset().container",
					"type": "Expression"
				}
			},
			"columnDelimiter": ",",
			"escapeChar": "\\",
			"firstRowAsHeader": true,
			"quoteChar": "\""
		},
		"schema": []
	}
}